wiki_as_base/__init__.py
wiki_as_base/cli.py
wiki_as_base/constants.py
wiki_as_base/parser.py
wiki_as_base/wiki_as_base.py
wiki_as_base-0.5.10.dist-info/LICENSE
wiki_as_base-0.5.10.dist-info/METADATA
wiki_as_base-0.5.10.dist-info/WHEEL
wiki_as_base-0.5.10.dist-info/entry_points.txt
wiki_as_base-0.5.10.dist-info/top_level.txt
wiki_as_base-0.5.10.dist-info/RECORD
