Metadata-Version: 2.1
Name: wiki-as-base
Version: 0.5.10
Summary: Use MediaWiki Wiki page content as read-only database
Home-page: https://github.com/fititnt/wiki_as_base-py
Author: Emerson Rocha
Author-email: rocha@ieee.org
Project-URL: Bug Tracker, https://github.com/fititnt/wiki_as_base-py/issues
Classifier: Programming Language :: Python :: 3
Classifier: License :: OSI Approved :: The Unlicense (Unlicense)
Classifier: Operating System :: OS Independent
Classifier: Typing :: Typed
Classifier: Topic :: Utilities
Requires-Python: >=3.7
License-File: LICENSE
Requires-Dist: requests
Requires-Dist: requests-cache
Requires-Dist: wikitextparser
